jsonut/__init__.py
tests/__init__.py
tests/test.py
jsonut-0.1.0.dist-info/LICENSE
jsonut-0.1.0.dist-info/METADATA
jsonut-0.1.0.dist-info/WHEEL
jsonut-0.1.0.dist-info/top_level.txt
jsonut-0.1.0.dist-info/RECORD
