Metadata-Version: 2.1
Name: jsonut
Version: 0.1.0
Summary: JSON Dataclass Object Mapper
Home-page: https://github.com/positive-man/jsonut
Author: wookjae.jo
Author-email: jwj0104@gmail.com
License: UNKNOWN
Platform: UNKNOWN
Classifier: Programming Language :: Python :: 3
Classifier: License :: OSI Approved :: GNU General Public License v3 (GPLv3)
Classifier: Operating System :: OS Independent
Requires-Python: >=3.6
